gpplus/__init__.py
gpplus/datasets/HOIP_noisy.py
gpplus/datasets/__init__.py
gpplus/kernels/Rough_RBF.py
gpplus/kernels/__init__.py
gpplus/kernels/matern.py
gpplus/kernels/wighted_RBF.py
gpplus/kernels/wighted_RBF_Z.py
gpplus/likelihoods_noise/__init__.py
gpplus/likelihoods_noise/multifidelity.py
gpplus/models/__init__.py
gpplus/models/gp_plus.py
gpplus/models/gpregression.py
gpplus/models/lvgp.py
gpplus/optim/__init__.py
gpplus/optim/mll_noise_tune.py
gpplus/optim/mll_noise_tune2.py
gpplus/optim/mll_noise_tune3.py
gpplus/optim/mll_scipy.py
gpplus/optim/mll_torch.py
gpplus/preprocessing/Data_reader.py
gpplus/preprocessing/__init__.py
gpplus/preprocessing/normalizeX.py
gpplus/preprocessing/numericlevels.py
gpplus/preprocessing/one_hot_encoding.py
gpplus/preprocessing/split.py
gpplus/priors/__init__.py
gpplus/priors/horseshoe.py
gpplus/priors/mollified_uniform.py
gpplus/test_functions/__init__.py
gpplus/test_functions/analytical.py
gpplus/test_functions/calibration_multi_fidelity.py
gpplus/test_functions/multi_fidelity.py
gpplus/utils/__init__.py
gpplus/utils/input_space.py
gpplus/utils/interval_score.py
gpplus/utils/set_seed.py
gpplus/utils/transforms.py
gpplus/utils/variables.py
gpplus/visual/__init__.py
gpplus/visual/plot_latent.py
gpplus/visual/plot_latenth.py
gpplus/visual/plot_latenth_position.py
gpplus-0.1.0.dist-info/METADATA
gpplus-0.1.0.dist-info/WHEEL
gpplus-0.1.0.dist-info/top_level.txt
gpplus-0.1.0.dist-info/RECORD
