Metadata-Version: 2.1
Name: gpplus
Version: 0.1.0
Summary: Python Library for Generalized Gaussian Process Modeling
Home-page: https://github.com/Bostanabad-Research-Group/GP-Plus
Author: Ramin Bostanabad, Amin Yousefpour
Author-email: yousefpo@uci.edu
Classifier: Programming Language :: Python :: 3
Classifier: License :: OSI Approved :: MIT License
Classifier: Operating System :: OS Independent
Requires-Python: >=3.6
Requires-Dist: numpy
Requires-Dist: scipy
Requires-Dist: torch
Requires-Dist: gpytorch
Requires-Dist: matplotlib
Requires-Dist: sobol-seq
Requires-Dist: tabulate
Requires-Dist: botorch
